{
    "stat:Document": {
        "-xmlns:stat": "https://casetext.com/stat",
        "-id": "rkkuqHjEtmMHJe_5So4F7fH1-_qroNKmf",
        "stat:Title": "California Code",
        "stat:URL": "https://leginfo.legislature.ca.gov/faces/codes.xhtml",
        "stat:Version": "0.1",
        "stat:Currency": "2017-07-07",
        "stat:Level": {
            "-id": "r1M_cSi4tmGS1mdqBs4YQMHy4_9HiEY7z",
            "-depth": "3",
            "-path": "/us/californiacode/California Code/Streets and Highways Code - SHC",
            "stat:Text": {
                "-xmlns:stat": "https://casetext.com/stat",
                "stat:Heading": "Streets and Highways Code - SHC"
            },
            "stat:Level": [
                {
                    "-id": "ry6cbe8s4t7fH1A5Wg8jEFXzB1JjWe8oEF7z",
                    "-path": "/us/californiacode/California Code/Streets and Highways Code - SHC/GENERAL PROVISIONS",
                    "stat:Text": {
                        "stat:heading": "GENERAL PROVISIONS",
                        "stat:Level": []
                    }
                },
                {
                    "-id": "HJmoZlIsVtmMB14sZlIoVFXMBkSoWgIjNtQM",
                    "-path": "/us/californiacode/California Code/Streets and Highways Code - SHC/DIVISION 1. STATE HIGHWAYS",
                    "stat:Text": {
                        "stat:heading": "DIVISION 1. STATE HIGHWAYS",
                        "stat:Level": []
                    }
                },
                {
                    "-id": "r1Fi-eLoEY7Grycj-g8i4tmGS1sj-eIoVFmG",
                    "-path": "/us/californiacode/California Code/Streets and Highways Code - SHC/DIVISION 2. COUNTY HIGHWAYS",
                    "stat:Text": {
                        "stat:heading": "DIVISION 2. COUNTY HIGHWAYS",
                        "stat:Level": []
                    }
                },
                {
                    "-id": "H1k2WxLiVY7GBJe3bgIoVY7GHyZ2ZeIjNtmG",
                    "-path": "/us/californiacode/California Code/Streets and Highways Code - SHC/DIVISION 2.5. CITY STREETS",
                    "stat:Text": {
                        "stat:heading": "DIVISION 2.5. CITY STREETS",
                        "stat:Level": []
                    }
                },
                {
                    "-id": "rJH3WxUoEtXfBk83-e8i4FmMryDnWe8sVKQG",
                    "-path": "/us/californiacode/California Code/Streets and Highways Code - SHC/DIVISION 2.7. COURTESY SIGNS",
                    "stat:Text": {
                        "stat:heading": "DIVISION 2.7. COURTESY SIGNS",
                        "stat:Level": []
                    }
                },
                {
                    "-id": "HJjnblUiVtXMBJnhWeUjNF7MHk62bg8j4YXG",
                    "-path": "/us/californiacode/California Code/Streets and Highways Code - SHC/DIVISION 3. APPORTIONMENT AND EXPENDITURE OF HIGHWAY FUNDS",
                    "stat:Text": {
                        "stat:heading": "DIVISION 3. APPORTIONMENT AND EXPENDITURE OF HIGHWAY FUNDS",
                        "stat:Level": []
                    }
                },
                {
                    "-id": "BJZaWl8i4FmGHkM6ZlLs4Y7zBy76bxIo4F7M",
                    "-path": "/us/californiacode/California Code/Streets and Highways Code - SHC/DIVISION 4. THE SPECIAL ASSESSMENT INVESTIGATION, LIMITATION AND MAJORITY PROTEST ACT OF 1931",
                    "stat:Text": {
                        "stat:heading": "DIVISION 4. THE SPECIAL ASSESSMENT INVESTIGATION, LIMITATION AND MAJORITY PROTEST ACT OF 1931",
                        "stat:Level": []
                    }
                },
                {
                    "-id": "BkPTblIjNFXfHJ_TbxIoEFXfBJK6be8oEYmG",
                    "-path": "/us/californiacode/California Code/Streets and Highways Code - SHC/DIVISION 4.5. NOTICE OF SPECIAL ASSESSMENT, SPECIAL TAX, AND FORECLOSURE PROCEEDINGS",
                    "stat:Text": {
                        "stat:heading": "DIVISION 4.5. NOTICE OF SPECIAL ASSESSMENT, SPECIAL TAX, AND FORECLOSURE PROCEEDINGS",
                        "stat:Level": []
                    }
                },
                {
                    "-id": "rJp6WgIs4KmfBk0pWe8sVF7fBJ10-l8s4Y7M",
                    "-path": "/us/californiacode/California Code/Streets and Highways Code - SHC/DIVISION 7. THE IMPROVEMENT ACT OF 1911",
                    "stat:Text": {
                        "stat:heading": "DIVISION 7. THE IMPROVEMENT ACT OF 1911",
                        "stat:Level": []
                    }
                },
                {
                    "-id": "SJXCbg8sEYXfrJNCZeIi4Fmzr1HCbxUiNFQM",
                    "-path": "/us/californiacode/California Code/Streets and Highways Code - SHC/DIVISION 9. CHANGE OF GRADE AND VACATION",
                    "stat:Text": {
                        "stat:heading": "DIVISION 9. CHANGE OF GRADE AND VACATION",
                        "stat:Level": []
                    }
                },
                {
                    "-id": "H1FA-eUs4tmGBJcAZe8j4FmGr1s0ZeUoNKXf",
                    "-path": "/us/californiacode/California Code/Streets and Highways Code - SHC/DIVISION 10. THE IMPROVEMENT BOND ACT OF 1915",
                    "stat:Text": {
                        "stat:heading": "DIVISION 10. THE IMPROVEMENT BOND ACT OF 1915",
                        "stat:Level": []
                    }
                },
                {
                    "-id": "r1kkMxLo4YXGBJxkfeUiNtQGrJZkfgLoNtQz",
                    "-path": "/us/californiacode/California Code/Streets and Highways Code - SHC/DIVISION 11. REFUNDING OF BONDS ISSUED UNDER THE “IMPROVEMENT BOND ACT OF 1915”",
                    "stat:Text": {
                        "stat:heading": "DIVISION 11. REFUNDING OF BONDS ISSUED UNDER THE “IMPROVEMENT BOND ACT OF 1915”",
                        "stat:Level": []
                    }
                },
                {
                    "-id": "HkBkGlUiEtQzryLkGe8j4Y7MS1PkGl8oVY7z",
                    "-path": "/us/californiacode/California Code/Streets and Highways Code - SHC/DIVISION 11.5. REFUNDING ACT OF 1984 FOR 1915 IMPROVEMENT ACT BONDS",
                    "stat:Text": {
                        "stat:heading": "DIVISION 11.5. REFUNDING ACT OF 1984 FOR 1915 IMPROVEMENT ACT BONDS",
                        "stat:Level": []
                    }
                },
                {
                    "-id": "H1syzx8jNF7MSJhyMg8o4Y7GHy6yzgIiNF7z",
                    "-path": "/us/californiacode/California Code/Streets and Highways Code - SHC/DIVISION 12. THE MUNICIPAL IMPROVEMENT ACT OF 1913",
                    "stat:Text": {
                        "stat:heading": "DIVISION 12. THE MUNICIPAL IMPROVEMENT ACT OF 1913",
                        "stat:Level": []
                    }
                },
                {
                    "-id": "BybxzeLjEFQfrkGlGe8jEFQzSkQgGe8oNFXz",
                    "-path": "/us/californiacode/California Code/Streets and Highways Code - SHC/DIVISION 13. PEDESTRIAN MALLS",
                    "stat:Text": {
                        "stat:heading": "DIVISION 13. PEDESTRIAN MALLS",
                        "stat:Level": []
                    }
                },
                {
                    "-id": "B1vxGeIjVt7MBkdezlIiNYXGrJFgMxUj4tQz",
                    "-path": "/us/californiacode/California Code/Streets and Highways Code - SHC/DIVISION 14. STREET LIGHTING",
                    "stat:Text": {
                        "stat:heading": "DIVISION 14. STREET LIGHTING",
                        "stat:Level": []
                    }
                },
                {
                    "-id": "HypeGgLjVK7zH1RgMxIsNY7GSJk-MeUi4tmf",
                    "-path": "/us/californiacode/California Code/Streets and Highways Code - SHC/DIVISION 15. TREE PLANTING, LANDSCAPING, AND LIGHTING",
                    "stat:Text": {
                        "stat:heading": "DIVISION 15. TREE PLANTING, LANDSCAPING, AND LIGHTING",
                        "stat:Level": []
                    }
                },
                {
                    "-id": "rJQWzl8sEKQMSJN-fgLoEK7MHyBZfeLsNFXG",
                    "-path": "/us/californiacode/California Code/Streets and Highways Code - SHC/DIVISION 16. HIGHWAY DISTRICTS",
                    "stat:Text": {
                        "stat:heading": "DIVISION 16. HIGHWAY DISTRICTS",
                        "stat:Level": []
                    }
                },
                {
                    "-id": "B1KZzlUo4t7fByq-MeUsEFmzrJjZGeUoVtXz",
                    "-path": "/us/californiacode/California Code/Streets and Highways Code - SHC/DIVISION 17. TOLL FACILITIES AND RELATED MATTERS",
                    "stat:Text": {
                        "stat:heading": "DIVISION 17. TOLL FACILITIES AND RELATED MATTERS",
                        "stat:Level": []
                    }
                },
                {
                    "-id": "BkJfGxUjNYmMSygGMeUoEtXfBJWfzeIiVtXG",
                    "-path": "/us/californiacode/California Code/Streets and Highways Code - SHC/DIVISION 18. PARKING",
                    "stat:Text": {
                        "stat:heading": "DIVISION 18. PARKING",
                        "stat:Level": []
                    }
                },
                {
                    "-id": "HJJUZgLs4KQGH1e8bgUjVtXzBJbLbgUs4YXz",
                    "-path": "/us/californiacode/California Code/Public Utilities Code - PUC/DIVISION 12.7. COUNTY AND REGIONAL TRANSPORTATION COMMISSIONS",
                    "stat:Text": {
                        "stat:heading": "DIVISION 12.7. COUNTY AND REGIONAL TRANSPORTATION COMMISSIONS",
                        "stat:Level": []
                    }
                },
                {
                    "-id": "Bkr8Zg8sVY7GByU8bxUiNtQMr1P8Zg8jEtQM",
                    "-path": "/us/californiacode/California Code/Public Utilities Code - PUC/DIVISION 12.8. Imperial County Transportation Commission",
                    "stat:Text": {
                        "stat:heading": "DIVISION 12.8. Imperial County Transportation Commission",
                        "stat:Level": []
                    }
                },
                {
                    "-id": "HJoIblUs4FXzBk2UZxUo4KQfH1pIZgIsVY7G",
                    "-path": "/us/californiacode/California Code/Public Utilities Code - PUC/DIVISION 13.1. SANTA CLARA COUNTY TRAFFIC AUTHORITY",
                    "stat:Text": {
                        "stat:heading": "DIVISION 13.1. SANTA CLARA COUNTY TRAFFIC AUTHORITY",
                        "stat:Level": []
                    }
                },
                {
                    "-id": "rkZPZe8oEFmfByfw-g8jVF7zSy7wWxLoEFQG",
                    "-path": "/us/californiacode/California Code/Public Utilities Code - PUC/DIVISION 14. COACHELLA VALLEY INTERMODAL TRANSPORTATION AUTHORITY",
                    "stat:Text": {
                        "stat:heading": "DIVISION 14. COACHELLA VALLEY INTERMODAL TRANSPORTATION AUTHORITY",
                        "stat:Level": []
                    }
                },
                {
                    "-id": "BkDvZxIiVFXzryOPWeUjVtmfSkYDblIiNt7f",
                    "-path": "/us/californiacode/California Code/Public Utilities Code - PUC/DIVISION 15. FRESNO COUNTY TRANSPORTATION AUTHORITY",
                    "stat:Text": {
                        "stat:heading": "DIVISION 15. FRESNO COUNTY TRANSPORTATION AUTHORITY",
                        "stat:Level": []
                    }
                },
                {
                    "-id": "HJTwWeIiNY7fryADWgIjNKQGr11OWeUiEt7f",
                    "-path": "/us/californiacode/California Code/Public Utilities Code - PUC/DIVISION 15.5. TUOLUMNE COUNTY TRAFFIC AUTHORITY",
                    "stat:Text": {
                        "stat:heading": "DIVISION 15.5. TUOLUMNE COUNTY TRAFFIC AUTHORITY",
                        "stat:Level": []
                    }
                },
                {
                    "-id": "rkXu-g8jEKQGr1VuZxLoVt7GBJSu-xIoEKQM",
                    "-path": "/us/californiacode/California Code/Public Utilities Code - PUC/DIVISION 16. PENINSULA RAIL TRANSIT DISTRICT",
                    "stat:Text": {
                        "stat:heading": "DIVISION 16. PENINSULA RAIL TRANSIT DISTRICT",
                        "stat:Level": []
                    }
                },
                {
                    "-id": "SyK_WgIoEY7fHycu-gUiVtXMBJjO-xLi4t7M",
                    "-path": "/us/californiacode/California Code/Public Utilities Code - PUC/DIVISION 16.5. STATE TRANSPORTATION CORRIDOR PRESERVATION",
                    "stat:Text": {
                        "stat:heading": "DIVISION 16.5. STATE TRANSPORTATION CORRIDOR PRESERVATION",
                        "stat:Level": []
                    }
                },
                {
                    "-id": "rJJFWeIoEYQGSkxFbgUoNYQzHyZtbxUiEFQz",
                    "-path": "/us/californiacode/California Code/Public Utilities Code - PUC/DIVISION 17. SAN DIEGO COUNTY REGIONAL AIRPORT AUTHORITY",
                    "stat:Text": {
                        "stat:heading": "DIVISION 17. SAN DIEGO COUNTY REGIONAL AIRPORT AUTHORITY",
                        "stat:Level": []
                    }
                },
                {
                    "-id": "SyHtbxLoNYmfSJ8tWlIoEFXfHyDKZxUoNKXM",
                    "-path": "/us/californiacode/California Code/Public Utilities Code - PUC/DIVISION 19. LOCAL TRANSPORTATION AUTHORITIES",
                    "stat:Text": {
                        "stat:heading": "DIVISION 19. LOCAL TRANSPORTATION AUTHORITIES",
                        "stat:Level": []
                    }
                },
                {
                    "-id": "rJoY-lUiNK7GSy2YZxIjVtXzBJat-e8j4FQG",
                    "-path": "/us/californiacode/California Code/Public Utilities Code - PUC/DIVISION 19.1. SONOMA COUNTY REGIONAL CLIMATE PROTECTION AUTHORITY",
                    "stat:Text": {
                        "stat:heading": "DIVISION 19.1. SONOMA COUNTY REGIONAL CLIMATE PROTECTION AUTHORITY",
                        "stat:Level": []
                    }
                },
                {
                    "-id": "Bk-c-lIjNt7MHkG5WeUjEFmzByXcbl8iNtXf",
                    "-path": "/us/californiacode/California Code/Public Utilities Code - PUC/DIVISION 19.5. CALIFORNIA HIGH-SPEED RAIL SERVICE",
                    "stat:Text": {
                        "stat:heading": "DIVISION 19.5. CALIFORNIA HIGH-SPEED RAIL SERVICE",
                        "stat:Level": []
                    }
                },
                {
                    "-id": "H1v5-eUs4FXMHyuqWgUi4tXzBJt9-gUoNY7z",
                    "-path": "/us/californiacode/California Code/Public Utilities Code - PUC/DIVISION 25. RIVERSIDE COUNTY TRANSPORTATION COMMISSION",
                    "stat:Text": {
                        "stat:heading": "DIVISION 25. RIVERSIDE COUNTY TRANSPORTATION COMMISSION",
                        "stat:Level": []
                    }
                },
                {
                    "-id": "HJSogUj4tmzHkUieIsEKQzBJwigLsVYXM",
                    "-path": "/us/californiacode/California Code/Public Resources Code - PRC/DIVISION 15. ENERGY CONSERVATION AND DEVELOPMENT",
                    "stat:Text": {
                        "stat:heading": "DIVISION 15. ENERGY CONSERVATION AND DEVELOPMENT",
                        "stat:Level": []
                    }
                },
                {
                    "-id": "SkiseIoNYQMHy2oeLj4t7Gr16slUiVFQG",
                    "-path": "/us/californiacode/California Code/Public Resources Code - PRC/DIVISION 16. CALIFORNIA ALTERNATIVE ENERGY AND ADVANCED TRANSPORTATION FINANCING AUTHORITY ACT",
                    "stat:Text": {
                        "stat:heading": "DIVISION 16. CALIFORNIA ALTERNATIVE ENERGY AND ADVANCED TRANSPORTATION FINANCING AUTHORITY ACT",
                        "stat:Level": []
                    }
                },
                {
                    "-id": "S1WheUjEKXGByfnxLs4t7GS173x8sEFXG",
                    "-path": "/us/californiacode/California Code/Public Resources Code - PRC/DIVISION 16.3. CLEAN ENERGY JOB CREATION",
                    "stat:Text": {
                        "stat:heading": "DIVISION 16.3. CLEAN ENERGY JOB CREATION",
                        "stat:Level": []
                    }
                },
                {
                    "-id": "ryPhxIiVF7MH1_hx8oEFXGSyKnlLiEtQf",
                    "-path": "/us/californiacode/California Code/Public Resources Code - PRC/DIVISION 16.5. ENERGY AND RESOURCES FUND",
                    "stat:Text": {
                        "stat:heading": "DIVISION 16.5. ENERGY AND RESOURCES FUND",
                        "stat:Level": []
                    }
                },
                {
                    "-id": "Hkp2xUjNtQzH1C3lLsEFXfrkyTg8oVtmz",
                    "-path": "/us/californiacode/California Code/Public Resources Code - PRC/DIVISION 17. GEOLOGIC HAZARD ABATEMENT DISTRICTS",
                    "stat:Text": {
                        "stat:heading": "DIVISION 17. GEOLOGIC HAZARD ABATEMENT DISTRICTS",
                        "stat:Level": []
                    }
                },
                {
                    "-id": "H1mpgIoEYQGHJV6xUo4KXMB1S6e8j4K7f",
                    "-path": "/us/californiacode/California Code/Public Resources Code - PRC/DIVISION 18. MORRO BAY MANAGEMENT PLAN",
                    "stat:Text": {
                        "stat:heading": "DIVISION 18. MORRO BAY MANAGEMENT PLAN",
                        "stat:Level": []
                    }
                },
                {
                    "-id": "BkF6gUoVtQzBJcTlUsEYmfrkiTg8iEFmz",
                    "-path": "/us/californiacode/California Code/Public Resources Code - PRC/DIVISION 19. SUISUN MARSH PRESERVATION",
                    "stat:Text": {
                        "stat:heading": "DIVISION 19. SUISUN MARSH PRESERVATION",
                        "stat:Level": []
                    }
                },
                {
                    "-id": "ryyCl8s4KmMHygRlLi4tQzByZAl8j4t7f",
                    "-path": "/us/californiacode/California Code/Public Resources Code - PRC/DIVISION 19.5. DELTA PROTECTION ACT OF 1992",
                    "stat:Text": {
                        "stat:heading": "DIVISION 19.5. DELTA PROTECTION ACT OF 1992",
                        "stat:Level": []
                    }
                },
                {
                    "-id": "SkBRxIsEtmfHJURlLj4FmzB1D0xUiNY7f",
                    "-path": "/us/californiacode/California Code/Public Resources Code - PRC/DIVISION 20. CALIFORNIA COASTAL ACT",
                    "stat:Text": {
                        "stat:heading": "DIVISION 20. CALIFORNIA COASTAL ACT",
                        "stat:Level": []
                    }
                },
                {
                    "-id": "HJs0gLiNKmfH13ClLsVFXfH16AeLjVtXz",
                    "-path": "/us/californiacode/California Code/Public Resources Code - PRC/DIVISION 20.4. WATERSHED, CLEAN BEACHES, AND WATER QUALITY ACT",
                    "stat:Text": {
                        "stat:heading": "DIVISION 20.4. WATERSHED, CLEAN BEACHES, AND WATER QUALITY ACT",
                        "stat:Level": []
                    }
                },
                {
                    "-id": "ryWJggUiVtQGHkz1lgUsEKQfrkXyxe8i4FXG",
                    "-path": "/us/californiacode/California Code/Public Resources Code - PRC/DIVISION 20.5. OCEAN USE PLANNING",
                    "stat:Text": {
                        "stat:heading": "DIVISION 20.5. OCEAN USE PLANNING",
                        "stat:Level": []
                    }
                },
                {
                    "-id": "ryPyge8o4FXfHkukxlUsVYXGHkFyglUjNY7f",
                    "-path": "/us/californiacode/California Code/Public Resources Code - PRC/DIVISION 20.6. Planning for Sea Level Rise Database",
                    "stat:Text": {
                        "stat:heading": "DIVISION 20.6. Planning for Sea Level Rise Database",
                        "stat:Level": []
                    }
                },
                {
                    "-id": "SkaJlxIj4KmfS10kllLsNKXfSJJlxeUjVY7z",
                    "-path": "/us/californiacode/California Code/Public Resources Code - PRC/DIVISION 20.7. SANTA MONICA BAY RESTORATION",
                    "stat:Text": {
                        "stat:heading": "DIVISION 20.7. SANTA MONICA BAY RESTORATION",
                        "stat:Level": []
                    }
                },
                {
                    "-id": "Hy7gleLiVt7Gr1Nexx8sEFXzHyrelgIo4YQf",
                    "-path": "/us/californiacode/California Code/Public Resources Code - PRC/DIVISION 21. STATE COASTAL CONSERVANCY",
                    "stat:Text": {
                        "stat:heading": "DIVISION 21. STATE COASTAL CONSERVANCY",
                        "stat:Level": []
                    }
                },
                {
                    "-id": "ryFell8sNYXGrJ5eglIiVKQMS1sgxx8o4F7G",
                    "-path": "/us/californiacode/California Code/Public Resources Code - PRC/DIVISION 22. CALIFORNIA URBAN WATERFRONT AREA RESTORATION FINANCING AUTHORITY ACT",
                    "stat:Text": {
                        "stat:heading": "DIVISION 22. CALIFORNIA URBAN WATERFRONT AREA RESTORATION FINANCING AUTHORITY ACT",
                        "stat:Level": []
                    }
                },
                {
                    "-id": "SykWggUiNtQfBJlbxxIs4FXzry--le8sNY7z",
                    "-path": "/us/californiacode/California Code/Public Resources Code - PRC/DIVISION 22.3. SACRAMENTO-SAN JOAQUIN DELTA CONSERVANCY",
                    "stat:Text": {
                        "stat:heading": "DIVISION 22.3. SACRAMENTO-SAN JOAQUIN DELTA CONSERVANCY",
                        "stat:Level": []
                    }
                },
                {
                    "-id": "r1HZgx8oNYXGry8Zex8oNYXfHyDWlgUoEYmG",
                    "-path": "/us/californiacode/California Code/Public Resources Code - PRC/DIVISION 22.5. SAN JOAQUIN RIVER CONSERVANCY",
                    "stat:Text": {
                        "stat:heading": "DIVISION 22.5. SAN JOAQUIN RIVER CONSERVANCY",
                        "stat:Level": []
                    }
                },
                {
                    "-id": "HJiZlgUj4YQfHJ2belUjNFmfBkT-lxLoVYXz",
                    "-path": "/us/californiacode/California Code/Public Resources Code - PRC/DIVISION 22.7. BALDWIN HILLS CONSERVANCY ACT",
                    "stat:Text": {
                        "stat:heading": "DIVISION 22.7. BALDWIN HILLS CONSERVANCY ACT",
                        "stat:Level": []
                    }
                },
                {
                    "-id": "SkWzel8jVY7fBJGGegLo4YmfrJ7zxeUsNFmz",
                    "-path": "/us/californiacode/California Code/Public Resources Code - PRC/DIVISION 22.8. SAN GABRIEL AND LOWER LOS ANGELES RIVERS AND MOUNTAINS CONSERVANCY",
                    "stat:Text": {
                        "stat:heading": "DIVISION 22.8. SAN GABRIEL AND LOWER LOS ANGELES RIVERS AND MOUNTAINS CONSERVANCY",
                        "stat:Level": []
                    }
                },
                {
                    "-id": "SJvMxgLiNF7MrkdMleUjVKQfSJKGxlUoEY7G",
                    "-path": "/us/californiacode/California Code/Public Resources Code - PRC/DIVISION 22.9. SAN DIEGO RIVER CONSERVANCY",
                    "stat:Text": {
                        "stat:heading": "DIVISION 22.9. SAN DIEGO RIVER CONSERVANCY",
                        "stat:Level": []
                    }
                },
                {
                    "-id": "SkpzelUjEFXzS1CMggUsEt7zry1Qlg8i4Kmf",
                    "-path": "/us/californiacode/California Code/Public Resources Code - PRC/DIVISION 23. SANTA MONICA MOUNTAINS CONSERVANCY",
                    "stat:Text": {
                        "stat:heading": "DIVISION 23. SANTA MONICA MOUNTAINS CONSERVANCY",
                        "stat:Level": []
                    }
                },
                {
                    "-id": "HkQ7lgIsVF7zH1NQggLjNY7zrJrXxxLj4YmM",
                    "-path": "/us/californiacode/California Code/Public Resources Code - PRC/DIVISION 23.3. SIERRA NEVADA CONSERVANCY",
                    "stat:Text": {
                        "stat:heading": "DIVISION 23.3. SIERRA NEVADA CONSERVANCY",
                        "stat:Level": []
                    }
                },
                {
                    "-id": "r1YQxgUoNtmMBJqQlg8sEFQGHJiQelUoNKmf",
                    "-path": "/us/californiacode/California Code/Public Resources Code - PRC/DIVISION 23.5. COACHELLA VALLEY MOUNTAINS CONSERVANCY",
                    "stat:Text": {
                        "stat:heading": "DIVISION 23.5. COACHELLA VALLEY MOUNTAINS CONSERVANCY",
                        "stat:Level": []
                    }
                },
                {
                    "-id": "r1J4xx8oVYmfH1g4xxLiVFmGr1bNgeIj4YXf",
                    "-path": "/us/californiacode/California Code/Public Resources Code - PRC/DIVISION 23.7. PRESERVATION OF FUTURE TRANSPORTATION OPTIONS",
                    "stat:Text": {
                        "stat:heading": "DIVISION 23.7. PRESERVATION OF FUTURE TRANSPORTATION OPTIONS",
                        "stat:Level": []
                    }
                },
                {
                    "-id": "HJSExe8sEYmGByUExlLjNFmzH1DEeeIoNtmz",
                    "-path": "/us/californiacode/California Code/Public Resources Code - PRC/DIVISION 24. RENEWABLE RESOURCES INVESTMENT PROGRAM",
                    "stat:Text": {
                        "stat:heading": "DIVISION 24. RENEWABLE RESOURCES INVESTMENT PROGRAM",
                        "stat:Level": []
                    }
                },
                {
                    "-id": "S1iNglUsVFXfS12Nex8jEtQzHkTVee8j4FXM",
                    "-path": "/us/californiacode/California Code/Public Resources Code - PRC/DIVISION 25. COASTAL RESOURCES AND ENERGY ASSISTANCE",
                    "stat:Text": {
                        "stat:heading": "DIVISION 25. COASTAL RESOURCES AND ENERGY ASSISTANCE",
                        "stat:Level": []
                    }
                },
                {
                    "-id": "By-Hle8s4YXfBkzBlxIi4t7fB17SlxLs4KQG",
                    "-path": "/us/californiacode/California Code/Public Resources Code - PRC/DIVISION 26. SANTA CLARA VALLEY OPEN-SPACE AUTHORITY",
                    "stat:Text": {
                        "stat:heading": "DIVISION 26. SANTA CLARA VALLEY OPEN-SPACE AUTHORITY",
                        "stat:Level": []
                    }
                },
                {
                    "-id": "ByPrlg8oNFXzHJOHgeUsEKQGH1trgxIoVKmz",
                    "-path": "/us/californiacode/California Code/Public Resources Code - PRC/DIVISION 26.5. CALIFORNIA OCEAN PROTECTION ACT",
                    "stat:Text": {
                        "stat:heading": "DIVISION 26.5. CALIFORNIA OCEAN PROTECTION ACT",
                        "stat:Level": []
                    }
                },
                {
                    "-id": "Sy6SxxLj4KmGSkRBel8i4KXMry18egLo4YQG",
                    "-path": "/us/californiacode/California Code/Public Resources Code - PRC/DIVISION 27. OCEAN RESOURCES MANAGEMENT",
                    "stat:Text": {
                        "stat:heading": "DIVISION 27. OCEAN RESOURCES MANAGEMENT",
                        "stat:Level": []
                    }
                },
                {
                    "-id": "H1m8geIjEt7zSyVIlgUiNtXfSyB8lgUsNKXf",
                    "-path": "/us/californiacode/California Code/Public Resources Code - PRC/DIVISION 28. NATURAL HERITAGE PRESERVATION TAX CREDIT ACT OF 2000",
                    "stat:Text": {
                        "stat:heading": "DIVISION 28. NATURAL HERITAGE PRESERVATION TAX CREDIT ACT OF 2000",
                        "stat:Level": []
                    }
                },
                {
                    "-id": "HyF8leLj4KQzHy98ee8oVYQGBkiUleUs4YQG",
                    "-path": "/us/californiacode/California Code/Public Resources Code - PRC/DIVISION 30. WASTE MANAGEMENT",
                    "stat:Text": {
                        "stat:heading": "DIVISION 30. WASTE MANAGEMENT",
                        "stat:Level": []
                    }
                },
                {
                    "-id": "HJyvlgIiNYQfBJgDelIoEKmzHk-Pgl8sVYmz",
                    "-path": "/us/californiacode/California Code/Public Resources Code - PRC/DIVISION 31. WASTE MANAGEMENT FACILITIES",
                    "stat:Text": {
                        "stat:heading": "DIVISION 31. WASTE MANAGEMENT FACILITIES",
                        "stat:Level": []
                    }
                },
                {
                    "-id": "HJBvglLsEKmGSy8wxgUiEFQzByPPelIoNt7M",
                    "-path": "/us/californiacode/California Code/Public Resources Code - PRC/DIVISION 33. GLASS CONTAMINATION",
                    "stat:Text": {
                        "stat:heading": "DIVISION 33. GLASS CONTAMINATION",
                        "stat:Level": []
                    }
                },
                {
                    "-id": "ryovxlUjEYXfHJ3DlgLsVF7GHkpwgeIsNYXf",
                    "-path": "/us/californiacode/California Code/Public Resources Code - PRC/DIVISION 34. ENVIRONMENTAL PROTECTION",
                    "stat:Text": {
                        "stat:heading": "DIVISION 34. ENVIRONMENTAL PROTECTION",
                        "stat:Level": []
                    }
                },
                {
                    "-id": "SJWdxxIi4FmGH1GuxlUoVF7zHy7OggUiEKmf",
                    "-path": "/us/californiacode/California Code/Public Resources Code - PRC/DIVISION 36. MARINE INVASIVE SPECIES ACT",
                    "stat:Text": {
                        "stat:heading": "DIVISION 36. MARINE INVASIVE SPECIES ACT",
                        "stat:Level": []
                    }
                },
                {
                    "-id": "rJwOeg8jVtmfrJ_Ogl8oVFQzr1tdeeUsVF7z",
                    "-path": "/us/californiacode/California Code/Public Resources Code - PRC/DIVISION 37. CALIFORNIA ENDOWMENT FOR MARINE PRESERVATION",
                    "stat:Text": {
                        "stat:heading": "DIVISION 37. CALIFORNIA ENDOWMENT FOR MARINE PRESERVATION",
                        "stat:Level": []
                    }
                },
                {
                    "-id": "B16degUoNYmGHJRdxeIo4FXzHkyKgeIj4tQM",
                    "-path": "/us/californiacode/California Code/Public Resources Code - PRC/DIVISION 38. CALIFORNIA CLEAN COAST ACT",
                    "stat:Text": {
                        "stat:heading": "DIVISION 38. CALIFORNIA CLEAN COAST ACT",
                        "stat:Level": []
                    }
                },
                {
                    "-id": "Sy7FggLiNKXMSyVtexUsNK7fS1HFllUoVKXG",
                    "-path": "/us/californiacode/California Code/Public Resources Code - PRC/DIVISION 43. THE SAFE DRINKING WATER, WATER QUALITY AND SUPPLY, FLOOD CONTROL, RIVER AND COASTAL PROTECTION BOND ACT OF 2006",
                    "stat:Text": {
                        "stat:heading": "DIVISION 43. THE SAFE DRINKING WATER, WATER QUALITY AND SUPPLY, FLOOD CONTROL, RIVER AND COASTAL PROTECTION BOND ACT OF 2006",
                        "stat:Level": []
                    }
                },
                {
                    "-id": "HyYtxl8jVtQfBycYxgLi4FXzHyitex8jVKQz",
                    "-path": "/us/californiacode/California Code/Public Resources Code - PRC/DIVISION 44. Transit, Affordable Housing, and Sustainable Communities Program",
                    "stat:Text": {
                        "stat:heading": "DIVISION 44. Transit, Affordable Housing, and Sustainable Communities Program",
                        "stat:Level": []
                    }
                }
            ]
        }
    }
}